mcp_pptx_tools-1.0.0.dist-info/licenses/LICENSE
powerpoint_mcp/__init__.py
powerpoint_mcp/server.py
mcp_pptx_tools-1.0.0.dist-info/METADATA
mcp_pptx_tools-1.0.0.dist-info/WHEEL
mcp_pptx_tools-1.0.0.dist-info/entry_points.txt
mcp_pptx_tools-1.0.0.dist-info/top_level.txt
mcp_pptx_tools-1.0.0.dist-info/RECORD
