Metadata-Version: 2.4
Name: mcp-pptx-tools
Version: 1.0.0
Summary: MCP server for creating and managing PowerPoint presentations using python-pptx
Author: PowerPoint MCP Contributors
License: MIT
Project-URL: Homepage, https://github.com/Prathush21/powerpoint-mcp
Project-URL: Documentation, https://github.com/Prathush21/powerpoint-mcp#readme
Project-URL: Repository, https://github.com/Prathush21/powerpoint-mcp
Project-URL: Issues, https://github.com/Prathush21/powerpoint-mcp/issues
Keywords: mcp,powerpoint,pptx,presentations,model-context-protocol
Classifier: Development Status :: 4 - Beta
Classifier: Intended Audience :: Developers
Classifier: License :: OSI Approved :: MIT License
Classifier: Programming Language :: Python :: 3
Classifier: Programming Language :: Python :: 3.10
Classifier: Programming Language :: Python :: 3.11
Classifier: Programming Language :: Python :: 3.12
Classifier: Topic :: Office/Business
Classifier: Topic :: Software Development :: Libraries :: Python Modules
Requires-Python: >=3.10
License-File: LICENSE
Requires-Dist: mcp>=1.0.0
Requires-Dist: python-pptx>=0.6.21
Requires-Dist: Pillow>=10.0.0
Provides-Extra: dev
Requires-Dist: pytest>=7.0.0; extra == "dev"
Requires-Dist: pytest-asyncio>=0.21.0; extra == "dev"
Requires-Dist: build>=0.10.0; extra == "dev"
Requires-Dist: twine>=4.0.0; extra == "dev"
Dynamic: license-file
